pelican/plugins/po4a/__init__.py
pelican/plugins/po4a/po4a.py
pelican/plugins/po4a/test_po4a.py
pelican_po4a-0.1.0.dist-info/WHEEL
pelican_po4a-0.1.0.dist-info/METADATA
pelican_po4a-0.1.0.dist-info/RECORD
