Metadata-Version: 2.1
Name: pelican-po4a
Version: 0.1.0
Summary: Pelican plugin for managing l10n with po4a
Home-page: https://edugit.org/Teckids/team-pr/pelican-po4a
License: Apache-2.0
Keywords: pelican,plugin,po4a,localisation,translation
Author: Dominik George
Author-email: dominik.george@teckids.org
Requires-Python: >=3.6.2,<4.0
Classifier: Development Status :: 2 - Pre-Alpha
Classifier: Environment :: Console
Classifier: Framework :: Pelican
Classifier: Framework :: Pelican :: Plugins
Classifier: Intended Audience :: End Users/Desktop
Classifier: License :: OSI Approved :: Apache Software License
Classifier: Operating System :: OS Independent
Classifier: Programming Language :: Python :: 3
Classifier: Programming Language :: Python :: 3.7
Classifier: Programming Language :: Python :: 3.8
Classifier: Programming Language :: Python :: 3.9
Classifier: Topic :: Internet :: WWW/HTTP
Classifier: Topic :: Software Development :: Libraries :: Python Modules
Requires-Dist: pelican (>=4.5)
Project-URL: Documentation, https://docs.getpelican.com
Project-URL: Funding, https://donate.getpelican.com/
Project-URL: Issue Tracker, https://edugit.org/Teckids/team-pr/pelican-po4a/-/issues
Project-URL: Repository, https://edugit.org/Teckids/team-pr/pelican-po4a
